[
  {
    "id": "1",
    "name": "Spider Man",
    "img": "/assets/spider-man.jpg",
    "lastMessage": "¡Hola Spider-Man!",
    "state": "entregado",
    "time": "9:15 am"
  },
  {
    "id": "2",
    "name": "Wolverine",
    "img": "/assets/wolverine.jpg",
    "lastMessage": "¿Cómo estás Wolverine?",
    "state": "leido" ,
    "time": "9:15 am"
  },
  {
    "id": "3",
    "name": "Capitan America",
    "img": "/assets/captain.jpg",
    "lastMessage": "Gracias por tu trabajo ",
    "state": "enviado" ,
    "time": "9:15 am"
  },
  {
    "id": "4",
    "name": "Deadpool",
    "img": "/assets/deadpool.jpg",
    "lastMessage": "¡Hola viejito! ",
    "state": "recibido" ,
    "time": "9:15 am"
  }
]